{
  "group": [
    {
      "group": {
        "name": "1111k"
      },
      "date": {
        "budget": "20000111111",
        "registration": "2023-01-01",
        "choosing": "2023-01-01",
        "exchange": "2023-01-01"
      },
      "admin": {
        "name": "44444",
        "email": "33333"
      },
      "gift": {},
      "id": 1
    },
    {
      "group": {
        "name": "g111"
      },
      "date": {
        "budget": "4444",
        "registration": "2023-01-29",
        "choosing": "2023-01-01",
        "exchange": "2023-01-01"
      },
      "admin": {
        "name": "2",
        "email": "2"
      },
      "gift": {
        "age": "2",
        "gender": "boy",
        "wishes": "2"
      },
      "id": 2
    }
  ],
  "user": [
    {
      "userDB": {
        "user": {
          "name": "",
          "email": "",
          "groupID": "2"
        }
      },
      "user": {
        "name": "",
        "email": "f"
      },
      "id": 1
    },
    {
      "userDB": {
        "user": {
          "name": "",
          "email": "",
          "groupID": "2"
        }
      },
      "user": {
        "name": "f",
        "email": "f"
      },
      "id": 2
    }
  ]
}